{
	"pages": [
		{
			"path": "pages/index/index",
			"style": {}
		},
		{
			"path": "pages/search/search",
			"style": {
				"navigationBarTitleText": "项目选址"
			}
		}
	],
	"style": "v2",
	"sitemapLocation": "sitemap.json",
	"permission": {
		"scope.userLocation": {
			"desc": "你的位置信息将用于小程序位置接口的效果展示"
		}
	},
	"easycom": {
		"autoscan": true,
		"custom": {
			"uni-(.*)": "@/components/uni-$1/uni-$1.vue",
			"html-content": "@/components/html-content/html-content.vue",
			"image-auto": "@/components/image-auto/image-auto.vue",
			"nav-bar": "@/components/nav-bar/nav-bar.vue",
			"popover": "@/components/popover/popover.vue",
			"rate": "@/components/rate/index.vue",
			"super-scroll-view": "@/components/super-scroll-view/super-scroll-view.vue",
			"suspension": "@/components/suspension/suspension.vue",
			"time-picker": "@/components/time-picker/time-picker.vue",
			"no-data": "@/components/no-data/no-data.vue",
			"loading": "@/components/loading/loading.vue",
			"qq-map": "@/components/qq-map/qq-map.vue"
		}
	},
	"globalStyle": {
		"backgroundTextStyle": "light",
		"navigationBarBackgroundColor": "#3486be",
		"navigationBarTitleText": "新密产业投资地图",
		"navigationBarTextStyle": "white"
	},
	"subPackages": [
		{
			"root": "xinmi",
			"pages": [
				{
					"path": "consult/consult",
					"style": {
						"navigationBarTitleText": "投资咨询"
					}
				},
				{
					"path": "details/details",
					"style": {
						"navigationBarTitleText": "资源详情"
					}
				},
				{
					"path": "resource/resource",
					"style": {}
				},
				{
					"path": "second/second",
					"style": {}
				}
			]
		}
	]
}